async_redis_objects/__init__.py
async_redis_objects/mocks.py
async_redis_objects/objects.py
async_redis_objects/test_objects.py
async_redis_objects-0.4.1.dist-info/LICENSE
async_redis_objects-0.4.1.dist-info/METADATA
async_redis_objects-0.4.1.dist-info/WHEEL
async_redis_objects-0.4.1.dist-info/top_level.txt
async_redis_objects-0.4.1.dist-info/RECORD
