Metadata-Version: 2.1
Name: async-redis-objects
Version: 0.4.1
Summary: Object oriented interface to aioredis.
Home-page: https://github.com/adam-douglass/async-redis-objects/
Author: Adam Douglass
Author-email: douglass@malloc.ca
License: UNKNOWN
Keywords: utility redis oop object-oriented
Platform: UNKNOWN
Requires-Dist: aioredis
Provides-Extra: docs
Requires-Dist: sphinx ; extra == 'docs'
Requires-Dist: sphinx-rtd-theme ; extra == 'docs'
Requires-Dist: sphinx-autodoc-typehints ; extra == 'docs'
Provides-Extra: test
Requires-Dist: pytest ; extra == 'test'
Requires-Dist: pytest-asyncio (!=0.11) ; extra == 'test'
Requires-Dist: coverage ; extra == 'test'
